{
  "metadata" : {
    "identifier" : "https://nghetruyenma.net/loi-nguyen-ngai-den.html",
    "title" : "Lời Nguyền Ngải Đen",
    "subtitle" : "N/A",
    "author" : {
      "name" : "Ngạ Quỷ",
      "sortAs" : ""
    },
    "narrator" : "N/A",
    "language" : "vi",
    "description" : "N/A",
    "publisher" : "N/A",
    "subject" : null,
    "modified" : null,
    "published" : "2023-06-27",
    "duration" : 4092,
    "abridged" : false,
    "conformsTo" : null,
    "numberOfPages" : null,
    "readingProgression" : null,
    "belongsTo" : null,
    "presentation" : null,
    "@type" : "http://schema.org/Audiobook",
    "schema:license" : "https://creativecommons.org/publicdomain/zero/1.0/"
  },
  "links" : [ {
    "rel" : "self",
    "href" : "https://raw.githubusercontent.com/vietduyhuynh90s/book_storage_two5/main/EPUB/EPUB_2c1b493f0e7879fe3a683dea30a0a416.json",
    "type" : "application/audiobook+json"
  }, {
    "rel" : "cover",
    "href" : "https://raw.githubusercontent.com/vietduyhuynh90s/book_storage_two5/main/IMAGE/IMAGE_2c1b493f0e7879fe3a683dea30a0a416.jpg",
    "type" : "image/jpeg",
    "height" : 300,
    "width" : 300
  } ],
  "readingOrder" : [ {
    "href" : "https://archive.org/download/loinguyenngaidenNTM/loi-nguyen-ngai-den.mp3",
    "type" : "audio/mpeg",
    "bitrate" : 128,
    "duration" : 4092,
    "title" : "loi-nguyen-ngai-den",
    "properties" : null,
    "alternate" : null
  } ],
  "toc" : [ {
    "href" : "https://archive.org/download/loinguyenngaidenNTM/loi-nguyen-ngai-den.mp3",
    "title" : "loi-nguyen-ngai-den",
    "children" : [ ]
  } ],
  "@context" : "https://readium.org/webpub-manifest/context.jsonld"
}