{
  "metadata" : {
    "identifier" : "https://www.nettruyento.com/truyen-tranh/ninja-shinobu-chan-no-junjou-172200",
    "title" : "Ninja Shinobu-chan no Junjou - Chapter 13",
    "subtitle" : null,
    "author" : null,
    "narrator" : null,
    "language" : "vi",
    "description" : null,
    "publisher" : "N/A",
    "subject" : null,
    "modified" : null,
    "published" : "2023-06-09",
    "duration" : 0,
    "abridged" : false,
    "conformsTo" : "https://readium.org/webpub-manifest/profiles/divina",
    "numberOfPages" : 30,
    "readingProgression" : "ttb",
    "belongsTo" : null,
    "presentation" : {
      "fit" : "width",
      "overflow" : "scrolled",
      "continuous" : true
    },
    "@type" : null,
    "schema:license" : null
  },
  "links" : [ {
    "rel" : "self",
    "href" : "https://raw.githubusercontent.com/thuvienonline40/book_storage_collection/main/comic_manifest.json",
    "type" : "application/divina+json"
  } ],
  "readingOrder" : [ {
    "href" : "https://raw.githubusercontent.com/duyhuynh652018/comic_storage5/main/IMAGE/IMAGE_20bef07ccee0cbae1de144f4f5748323_42915792e4eca1ef34ec880b1c367f61_a56a8dea32cd49831c909e2f52024f64.jpg",
    "type" : "image/jpeg",
    "bitrate" : 0,
    "duration" : 0,
    "title" : null,
    "properties" : null,
    "alternate" : [ {
      "href" : "https://i334.ntcdntempv3.com/data/images/17220/358584/001.jpg?data=net",
      "type" : "image/jpeg",
      "bitrate" : 0,
      "duration" : 0,
      "title" : null,
      "properties" : null,
      "alternate" : null
    } ]
  }, {
    "href" : "https://raw.githubusercontent.com/duyhuynh652018/comic_storage5/main/IMAGE/IMAGE_20bef07ccee0cbae1de144f4f5748323_42915792e4eca1ef34ec880b1c367f61_60ad58c428035e9fed21eb29fc7777ba.jpg",
    "type" : "image/jpeg",
    "bitrate" : 0,
    "duration" : 0,
    "title" : null,
    "properties" : null,
    "alternate" : [ {
      "href" : "https://i334.ntcdntempv3.com/data/images/17220/358584/002.jpg?data=net",
      "type" : "image/jpeg",
      "bitrate" : 0,
      "duration" : 0,
      "title" : null,
      "properties" : null,
      "alternate" : null
    } ]
  }, {
    "href" : "https://raw.githubusercontent.com/duyhuynh652018/comic_storage5/main/IMAGE/IMAGE_20bef07ccee0cbae1de144f4f5748323_42915792e4eca1ef34ec880b1c367f61_bc3a70c2be45b01954f8a116a138a178.jpg",
    "type" : "image/jpeg",
    "bitrate" : 0,
    "duration" : 0,
    "title" : null,
    "properties" : null,
    "alternate" : [ {
      "href" : "https://i334.ntcdntempv3.com/data/images/17220/358584/003.jpg?data=net",
      "type" : "image/jpeg",
      "bitrate" : 0,
      "duration" : 0,
      "title" : null,
      "properties" : null,
      "alternate" : null
    } ]
  }, {
    "href" : "https://raw.githubusercontent.com/duyhuynh652018/comic_storage5/main/IMAGE/IMAGE_20bef07ccee0cbae1de144f4f5748323_42915792e4eca1ef34ec880b1c367f61_e69a313e49f901b8409845771c86a653.jpg",
    "type" : "image/jpeg",
    "bitrate" : 0,
    "duration" : 0,
    "title" : null,
    "properties" : null,
    "alternate" : [ {
      "href" : "https://i334.ntcdntempv3.com/data/images/17220/358584/004.jpg?data=net",
      "type" : "image/jpeg",
      "bitrate" : 0,
      "duration" : 0,
      "title" : null,
      "properties" : null,
      "alternate" : null
    } ]
  }, {
    "href" : "https://raw.githubusercontent.com/duyhuynh652018/comic_storage5/main/IMAGE/IMAGE_20bef07ccee0cbae1de144f4f5748323_42915792e4eca1ef34ec880b1c367f61_4035f2ae56df6c1e61cbba04f475a81a.jpg",
    "type" : "image/jpeg",
    "bitrate" : 0,
    "duration" : 0,
    "title" : null,
    "properties" : null,
    "alternate" : [ {
      "href" : "https://i334.ntcdntempv3.com/data/images/17220/358584/005.jpg?data=net",
      "type" : "image/jpeg",
      "bitrate" : 0,
      "duration" : 0,
      "title" : null,
      "properties" : null,
      "alternate" : null
    } ]
  }, {
    "href" : "https://raw.githubusercontent.com/duyhuynh652018/comic_storage5/main/IMAGE/IMAGE_20bef07ccee0cbae1de144f4f5748323_42915792e4eca1ef34ec880b1c367f61_74e20bc27f680351c89f455f1a1a22cb.jpg",
    "type" : "image/jpeg",
    "bitrate" : 0,
    "duration" : 0,
    "title" : null,
    "properties" : null,
    "alternate" : [ {
      "href" : "https://i334.ntcdntempv3.com/data/images/17220/358584/006.jpg?data=net",
      "type" : "image/jpeg",
      "bitrate" : 0,
      "duration" : 0,
      "title" : null,
      "properties" : null,
      "alternate" : null
    } ]
  }, {
    "href" : "https://raw.githubusercontent.com/duyhuynh652018/comic_storage5/main/IMAGE/IMAGE_20bef07ccee0cbae1de144f4f5748323_42915792e4eca1ef34ec880b1c367f61_f5828883c2a8d645c37daf686a8532f4.jpg",
    "type" : "image/jpeg",
    "bitrate" : 0,
    "duration" : 0,
    "title" : null,
    "properties" : null,
    "alternate" : [ {
      "href" : "https://i334.ntcdntempv3.com/data/images/17220/358584/007.jpg?data=net",
      "type" : "image/jpeg",
      "bitrate" : 0,
      "duration" : 0,
      "title" : null,
      "properties" : null,
      "alternate" : null
    } ]
  }, {
    "href" : "https://raw.githubusercontent.com/duyhuynh652018/comic_storage5/main/IMAGE/IMAGE_20bef07ccee0cbae1de144f4f5748323_42915792e4eca1ef34ec880b1c367f61_f2306aca223f4cfb1c9cb01f79099f6c.jpg",
    "type" : "image/jpeg",
    "bitrate" : 0,
    "duration" : 0,
    "title" : null,
    "properties" : null,
    "alternate" : [ {
      "href" : "https://i334.ntcdntempv3.com/data/images/17220/358584/008.jpg?data=net",
      "type" : "image/jpeg",
      "bitrate" : 0,
      "duration" : 0,
      "title" : null,
      "properties" : null,
      "alternate" : null
    } ]
  }, {
    "href" : "https://raw.githubusercontent.com/duyhuynh652018/comic_storage5/main/IMAGE/IMAGE_20bef07ccee0cbae1de144f4f5748323_42915792e4eca1ef34ec880b1c367f61_6d183a0f323a60f6c092e220d40051e3.jpg",
    "type" : "image/jpeg",
    "bitrate" : 0,
    "duration" : 0,
    "title" : null,
    "properties" : null,
    "alternate" : [ {
      "href" : "https://i334.ntcdntempv3.com/data/images/17220/358584/009.jpg?data=net",
      "type" : "image/jpeg",
      "bitrate" : 0,
      "duration" : 0,
      "title" : null,
      "properties" : null,
      "alternate" : null
    } ]
  }, {
    "href" : "https://raw.githubusercontent.com/duyhuynh652018/comic_storage5/main/IMAGE/IMAGE_20bef07ccee0cbae1de144f4f5748323_42915792e4eca1ef34ec880b1c367f61_30bf4e0b72566b1f6f199df8dcf05ed1.jpg",
    "type" : "image/jpeg",
    "bitrate" : 0,
    "duration" : 0,
    "title" : null,
    "properties" : null,
    "alternate" : [ {
      "href" : "https://i334.ntcdntempv3.com/data/images/17220/358584/010.jpg?data=net",
      "type" : "image/jpeg",
      "bitrate" : 0,
      "duration" : 0,
      "title" : null,
      "properties" : null,
      "alternate" : null
    } ]
  }, {
    "href" : "https://raw.githubusercontent.com/duyhuynh652018/comic_storage5/main/IMAGE/IMAGE_20bef07ccee0cbae1de144f4f5748323_42915792e4eca1ef34ec880b1c367f61_fa8566fb3893a1f4316f74dfd1d54db9.jpg",
    "type" : "image/jpeg",
    "bitrate" : 0,
    "duration" : 0,
    "title" : null,
    "properties" : null,
    "alternate" : [ {
      "href" : "https://i334.ntcdntempv3.com/data/images/17220/358584/011.jpg?data=net",
      "type" : "image/jpeg",
      "bitrate" : 0,
      "duration" : 0,
      "title" : null,
      "properties" : null,
      "alternate" : null
    } ]
  }, {
    "href" : "https://raw.githubusercontent.com/duyhuynh652018/comic_storage5/main/IMAGE/IMAGE_20bef07ccee0cbae1de144f4f5748323_42915792e4eca1ef34ec880b1c367f61_91bd713c1bd95e140c84c91f758b4e24.jpg",
    "type" : "image/jpeg",
    "bitrate" : 0,
    "duration" : 0,
    "title" : null,
    "properties" : null,
    "alternate" : [ {
      "href" : "https://i334.ntcdntempv3.com/data/images/17220/358584/012.jpg?data=net",
      "type" : "image/jpeg",
      "bitrate" : 0,
      "duration" : 0,
      "title" : null,
      "properties" : null,
      "alternate" : null
    } ]
  }, {
    "href" : "https://raw.githubusercontent.com/duyhuynh652018/comic_storage5/main/IMAGE/IMAGE_20bef07ccee0cbae1de144f4f5748323_42915792e4eca1ef34ec880b1c367f61_fc61531ef95200f8e644457617d7ef2e.jpg",
    "type" : "image/jpeg",
    "bitrate" : 0,
    "duration" : 0,
    "title" : null,
    "properties" : null,
    "alternate" : [ {
      "href" : "https://i334.ntcdntempv3.com/data/images/17220/358584/013.jpg?data=net",
      "type" : "image/jpeg",
      "bitrate" : 0,
      "duration" : 0,
      "title" : null,
      "properties" : null,
      "alternate" : null
    } ]
  }, {
    "href" : "https://raw.githubusercontent.com/duyhuynh652018/comic_storage5/main/IMAGE/IMAGE_20bef07ccee0cbae1de144f4f5748323_42915792e4eca1ef34ec880b1c367f61_963db1b75f0083099f01b31c6bf8493f.jpg",
    "type" : "image/jpeg",
    "bitrate" : 0,
    "duration" : 0,
    "title" : null,
    "properties" : null,
    "alternate" : [ {
      "href" : "https://i334.ntcdntempv3.com/data/images/17220/358584/014.jpg?data=net",
      "type" : "image/jpeg",
      "bitrate" : 0,
      "duration" : 0,
      "title" : null,
      "properties" : null,
      "alternate" : null
    } ]
  }, {
    "href" : "https://raw.githubusercontent.com/duyhuynh652018/comic_storage5/main/IMAGE/IMAGE_20bef07ccee0cbae1de144f4f5748323_42915792e4eca1ef34ec880b1c367f61_82296fc2297edb45f3fba416ab7d003e.jpg",
    "type" : "image/jpeg",
    "bitrate" : 0,
    "duration" : 0,
    "title" : null,
    "properties" : null,
    "alternate" : [ {
      "href" : "https://i334.ntcdntempv3.com/data/images/17220/358584/015.jpg?data=net",
      "type" : "image/jpeg",
      "bitrate" : 0,
      "duration" : 0,
      "title" : null,
      "properties" : null,
      "alternate" : null
    } ]
  }, {
    "href" : "https://raw.githubusercontent.com/duyhuynh652018/comic_storage5/main/IMAGE/IMAGE_20bef07ccee0cbae1de144f4f5748323_42915792e4eca1ef34ec880b1c367f61_4d066586421d5e4471c226b14dfeab0f.jpg",
    "type" : "image/jpeg",
    "bitrate" : 0,
    "duration" : 0,
    "title" : null,
    "properties" : null,
    "alternate" : [ {
      "href" : "https://i334.ntcdntempv3.com/data/images/17220/358584/016.jpg?data=net",
      "type" : "image/jpeg",
      "bitrate" : 0,
      "duration" : 0,
      "title" : null,
      "properties" : null,
      "alternate" : null
    } ]
  }, {
    "href" : "https://raw.githubusercontent.com/duyhuynh652018/comic_storage5/main/IMAGE/IMAGE_20bef07ccee0cbae1de144f4f5748323_42915792e4eca1ef34ec880b1c367f61_357627e7f97f92e9590388e2aa84e774.jpg",
    "type" : "image/jpeg",
    "bitrate" : 0,
    "duration" : 0,
    "title" : null,
    "properties" : null,
    "alternate" : [ {
      "href" : "https://i334.ntcdntempv3.com/data/images/17220/358584/017.jpg?data=net",
      "type" : "image/jpeg",
      "bitrate" : 0,
      "duration" : 0,
      "title" : null,
      "properties" : null,
      "alternate" : null
    } ]
  }, {
    "href" : "https://raw.githubusercontent.com/duyhuynh652018/comic_storage5/main/IMAGE/IMAGE_20bef07ccee0cbae1de144f4f5748323_42915792e4eca1ef34ec880b1c367f61_eecdba6a7b68604f9b7ea81f51e7b714.jpg",
    "type" : "image/jpeg",
    "bitrate" : 0,
    "duration" : 0,
    "title" : null,
    "properties" : null,
    "alternate" : [ {
      "href" : "https://i334.ntcdntempv3.com/data/images/17220/358584/018.jpg?data=net",
      "type" : "image/jpeg",
      "bitrate" : 0,
      "duration" : 0,
      "title" : null,
      "properties" : null,
      "alternate" : null
    } ]
  }, {
    "href" : "https://raw.githubusercontent.com/duyhuynh652018/comic_storage5/main/IMAGE/IMAGE_20bef07ccee0cbae1de144f4f5748323_42915792e4eca1ef34ec880b1c367f61_c141eb1ee05a38252aacf7ff1314db10.jpg",
    "type" : "image/jpeg",
    "bitrate" : 0,
    "duration" : 0,
    "title" : null,
    "properties" : null,
    "alternate" : [ {
      "href" : "https://i334.ntcdntempv3.com/data/images/17220/358584/019.jpg?data=net",
      "type" : "image/jpeg",
      "bitrate" : 0,
      "duration" : 0,
      "title" : null,
      "properties" : null,
      "alternate" : null
    } ]
  }, {
    "href" : "https://raw.githubusercontent.com/duyhuynh652018/comic_storage5/main/IMAGE/IMAGE_20bef07ccee0cbae1de144f4f5748323_42915792e4eca1ef34ec880b1c367f61_4489f3fd4cf1e04378253bdcd6d577fc.jpg",
    "type" : "image/jpeg",
    "bitrate" : 0,
    "duration" : 0,
    "title" : null,
    "properties" : null,
    "alternate" : [ {
      "href" : "https://i334.ntcdntempv3.com/data/images/17220/358584/020.jpg?data=net",
      "type" : "image/jpeg",
      "bitrate" : 0,
      "duration" : 0,
      "title" : null,
      "properties" : null,
      "alternate" : null
    } ]
  }, {
    "href" : "https://raw.githubusercontent.com/duyhuynh652018/comic_storage5/main/IMAGE/IMAGE_20bef07ccee0cbae1de144f4f5748323_42915792e4eca1ef34ec880b1c367f61_5a5b2529b655b6c0d4123bf92ef6f359.jpg",
    "type" : "image/jpeg",
    "bitrate" : 0,
    "duration" : 0,
    "title" : null,
    "properties" : null,
    "alternate" : [ {
      "href" : "https://i334.ntcdntempv3.com/data/images/17220/358584/021.jpg?data=net",
      "type" : "image/jpeg",
      "bitrate" : 0,
      "duration" : 0,
      "title" : null,
      "properties" : null,
      "alternate" : null
    } ]
  }, {
    "href" : "https://raw.githubusercontent.com/duyhuynh652018/comic_storage5/main/IMAGE/IMAGE_20bef07ccee0cbae1de144f4f5748323_42915792e4eca1ef34ec880b1c367f61_a0182b7e5da43f92ac422cac390a344a.jpg",
    "type" : "image/jpeg",
    "bitrate" : 0,
    "duration" : 0,
    "title" : null,
    "properties" : null,
    "alternate" : [ {
      "href" : "https://i334.ntcdntempv3.com/data/images/17220/358584/022.jpg?data=net",
      "type" : "image/jpeg",
      "bitrate" : 0,
      "duration" : 0,
      "title" : null,
      "properties" : null,
      "alternate" : null
    } ]
  }, {
    "href" : "https://raw.githubusercontent.com/duyhuynh652018/comic_storage5/main/IMAGE/IMAGE_20bef07ccee0cbae1de144f4f5748323_42915792e4eca1ef34ec880b1c367f61_09fd708930b5d14cf1a88997c8898caf.jpg",
    "type" : "image/jpeg",
    "bitrate" : 0,
    "duration" : 0,
    "title" : null,
    "properties" : null,
    "alternate" : [ {
      "href" : "https://i334.ntcdntempv3.com/data/images/17220/358584/023.jpg?data=net",
      "type" : "image/jpeg",
      "bitrate" : 0,
      "duration" : 0,
      "title" : null,
      "properties" : null,
      "alternate" : null
    } ]
  }, {
    "href" : "https://raw.githubusercontent.com/duyhuynh652018/comic_storage5/main/IMAGE/IMAGE_20bef07ccee0cbae1de144f4f5748323_42915792e4eca1ef34ec880b1c367f61_042619bde55d82a42e78918f5c8f2ff1.jpg",
    "type" : "image/jpeg",
    "bitrate" : 0,
    "duration" : 0,
    "title" : null,
    "properties" : null,
    "alternate" : [ {
      "href" : "https://i334.ntcdntempv3.com/data/images/17220/358584/024.jpg?data=net",
      "type" : "image/jpeg",
      "bitrate" : 0,
      "duration" : 0,
      "title" : null,
      "properties" : null,
      "alternate" : null
    } ]
  }, {
    "href" : "https://raw.githubusercontent.com/duyhuynh652018/comic_storage5/main/IMAGE/IMAGE_20bef07ccee0cbae1de144f4f5748323_42915792e4eca1ef34ec880b1c367f61_99fac2e3e8e8b61cd9596adafe3b5b0e.jpg",
    "type" : "image/jpeg",
    "bitrate" : 0,
    "duration" : 0,
    "title" : null,
    "properties" : null,
    "alternate" : [ {
      "href" : "https://i334.ntcdntempv3.com/data/images/17220/358584/025.jpg?data=net",
      "type" : "image/jpeg",
      "bitrate" : 0,
      "duration" : 0,
      "title" : null,
      "properties" : null,
      "alternate" : null
    } ]
  }, {
    "href" : "https://raw.githubusercontent.com/duyhuynh652018/comic_storage5/main/IMAGE/IMAGE_20bef07ccee0cbae1de144f4f5748323_42915792e4eca1ef34ec880b1c367f61_9e56eebd8863b77b3cc108068a8a644b.jpg",
    "type" : "image/jpeg",
    "bitrate" : 0,
    "duration" : 0,
    "title" : null,
    "properties" : null,
    "alternate" : [ {
      "href" : "https://i334.ntcdntempv3.com/data/images/17220/358584/026.jpg?data=net",
      "type" : "image/jpeg",
      "bitrate" : 0,
      "duration" : 0,
      "title" : null,
      "properties" : null,
      "alternate" : null
    } ]
  }, {
    "href" : "https://raw.githubusercontent.com/duyhuynh652018/comic_storage5/main/IMAGE/IMAGE_20bef07ccee0cbae1de144f4f5748323_42915792e4eca1ef34ec880b1c367f61_28b2035cf6f7187cfa3af110251b1aa7.jpg",
    "type" : "image/jpeg",
    "bitrate" : 0,
    "duration" : 0,
    "title" : null,
    "properties" : null,
    "alternate" : [ {
      "href" : "https://i334.ntcdntempv3.com/data/images/17220/358584/027.jpg?data=net",
      "type" : "image/jpeg",
      "bitrate" : 0,
      "duration" : 0,
      "title" : null,
      "properties" : null,
      "alternate" : null
    } ]
  }, {
    "href" : "https://raw.githubusercontent.com/duyhuynh652018/comic_storage5/main/IMAGE/IMAGE_20bef07ccee0cbae1de144f4f5748323_42915792e4eca1ef34ec880b1c367f61_c741225f21907d4f949c506a2a89163a.jpg",
    "type" : "image/jpeg",
    "bitrate" : 0,
    "duration" : 0,
    "title" : null,
    "properties" : null,
    "alternate" : [ {
      "href" : "https://i334.ntcdntempv3.com/data/images/17220/358584/028.jpg?data=net",
      "type" : "image/jpeg",
      "bitrate" : 0,
      "duration" : 0,
      "title" : null,
      "properties" : null,
      "alternate" : null
    } ]
  }, {
    "href" : "https://raw.githubusercontent.com/duyhuynh652018/comic_storage5/main/IMAGE/IMAGE_20bef07ccee0cbae1de144f4f5748323_42915792e4eca1ef34ec880b1c367f61_0bb25264d41240d5c3857380bd5619a5.jpg",
    "type" : "image/jpeg",
    "bitrate" : 0,
    "duration" : 0,
    "title" : null,
    "properties" : null,
    "alternate" : [ {
      "href" : "https://i334.ntcdntempv3.com/data/images/17220/358584/029.jpg?data=net",
      "type" : "image/jpeg",
      "bitrate" : 0,
      "duration" : 0,
      "title" : null,
      "properties" : null,
      "alternate" : null
    } ]
  }, {
    "href" : "https://raw.githubusercontent.com/duyhuynh652018/comic_storage5/main/IMAGE/IMAGE_20bef07ccee0cbae1de144f4f5748323_42915792e4eca1ef34ec880b1c367f61_8a3977ee3d4813e80d76dc0286113ab8.jpg",
    "type" : "image/jpeg",
    "bitrate" : 0,
    "duration" : 0,
    "title" : null,
    "properties" : null,
    "alternate" : [ {
      "href" : "https://i334.ntcdntempv3.com/data/images/17220/358584/030.jpg?data=net",
      "type" : "image/jpeg",
      "bitrate" : 0,
      "duration" : 0,
      "title" : null,
      "properties" : null,
      "alternate" : null
    } ]
  }, {
    "href" : "https://raw.githubusercontent.com/duyhuynh652018/comic_storage5/main/IMAGE/IMAGE_20bef07ccee0cbae1de144f4f5748323_42915792e4eca1ef34ec880b1c367f61_dca75014cf8de7c03f51ad04892aca15.jpg",
    "type" : "image/jpeg",
    "bitrate" : 0,
    "duration" : 0,
    "title" : null,
    "properties" : null,
    "alternate" : [ {
      "href" : "https://i334.ntcdntempv3.com/data/images/17220/358584/031.jpg?data=net",
      "type" : "image/jpeg",
      "bitrate" : 0,
      "duration" : 0,
      "title" : null,
      "properties" : null,
      "alternate" : null
    } ]
  }, {
    "href" : "https://raw.githubusercontent.com/duyhuynh652018/comic_storage5/main/IMAGE/IMAGE_20bef07ccee0cbae1de144f4f5748323_42915792e4eca1ef34ec880b1c367f61_dced55634d3cf982932a23cd2c731e2c.jpg",
    "type" : "image/jpeg",
    "bitrate" : 0,
    "duration" : 0,
    "title" : null,
    "properties" : null,
    "alternate" : [ {
      "href" : "https://i334.ntcdntempv3.com/data/images/17220/358584/032.jpg?data=net",
      "type" : "image/jpeg",
      "bitrate" : 0,
      "duration" : 0,
      "title" : null,
      "properties" : null,
      "alternate" : null
    } ]
  }, {
    "href" : "https://raw.githubusercontent.com/duyhuynh652018/comic_storage5/main/IMAGE/IMAGE_20bef07ccee0cbae1de144f4f5748323_42915792e4eca1ef34ec880b1c367f61_de4411dc3f4feb6abf247802f140df57.jpg",
    "type" : "image/jpeg",
    "bitrate" : 0,
    "duration" : 0,
    "title" : null,
    "properties" : null,
    "alternate" : [ {
      "href" : "https://i334.ntcdntempv3.com/data/images/17220/358584/033.jpg?data=net",
      "type" : "image/jpeg",
      "bitrate" : 0,
      "duration" : 0,
      "title" : null,
      "properties" : null,
      "alternate" : null
    } ]
  }, {
    "href" : "https://raw.githubusercontent.com/duyhuynh652018/comic_storage5/main/IMAGE/IMAGE_20bef07ccee0cbae1de144f4f5748323_42915792e4eca1ef34ec880b1c367f61_6619c809807080b74c96cce062e3efba.jpg",
    "type" : "image/jpeg",
    "bitrate" : 0,
    "duration" : 0,
    "title" : null,
    "properties" : null,
    "alternate" : [ {
      "href" : "https://i334.ntcdntempv3.com/data/images/17220/358584/034.jpg?data=net",
      "type" : "image/jpeg",
      "bitrate" : 0,
      "duration" : 0,
      "title" : null,
      "properties" : null,
      "alternate" : null
    } ]
  }, {
    "href" : "https://raw.githubusercontent.com/duyhuynh652018/comic_storage5/main/IMAGE/IMAGE_20bef07ccee0cbae1de144f4f5748323_42915792e4eca1ef34ec880b1c367f61_fc73363f2c4bd9c5c15ebe12b56f506c.jpg",
    "type" : "image/jpeg",
    "bitrate" : 0,
    "duration" : 0,
    "title" : null,
    "properties" : null,
    "alternate" : [ {
      "href" : "https://i334.ntcdntempv3.com/data/images/17220/358584/035.jpg?data=net",
      "type" : "image/jpeg",
      "bitrate" : 0,
      "duration" : 0,
      "title" : null,
      "properties" : null,
      "alternate" : null
    } ]
  }, {
    "href" : "https://raw.githubusercontent.com/duyhuynh652018/comic_storage5/main/IMAGE/IMAGE_20bef07ccee0cbae1de144f4f5748323_42915792e4eca1ef34ec880b1c367f61_0f7f23285d708a81e89a2684c7a506bd.jpg",
    "type" : "image/jpeg",
    "bitrate" : 0,
    "duration" : 0,
    "title" : null,
    "properties" : null,
    "alternate" : [ {
      "href" : "https://i334.ntcdntempv3.com/data/images/17220/358584/036.jpg?data=net",
      "type" : "image/jpeg",
      "bitrate" : 0,
      "duration" : 0,
      "title" : null,
      "properties" : null,
      "alternate" : null
    } ]
  }, {
    "href" : "https://raw.githubusercontent.com/duyhuynh652018/comic_storage5/main/IMAGE/IMAGE_20bef07ccee0cbae1de144f4f5748323_42915792e4eca1ef34ec880b1c367f61_ea26bf0d0e27efb57f08677472dc6570.jpg",
    "type" : "image/jpeg",
    "bitrate" : 0,
    "duration" : 0,
    "title" : null,
    "properties" : null,
    "alternate" : [ {
      "href" : "https://i334.ntcdntempv3.com/data/images/17220/358584/037.jpg?data=net",
      "type" : "image/jpeg",
      "bitrate" : 0,
      "duration" : 0,
      "title" : null,
      "properties" : null,
      "alternate" : null
    } ]
  } ],
  "toc" : null,
  "@context" : "https://readium.org/webpub-manifest/context.jsonld"
}