{
  "metadata" : {
    "identifier" : "https://www.nettruyento.com/truyen-tranh/con-tim-rung-dong-2-182450",
    "title" : "Con tim rung động 2 - Chapter 69",
    "subtitle" : null,
    "author" : null,
    "narrator" : null,
    "language" : "vi",
    "description" : null,
    "publisher" : "N/A",
    "subject" : null,
    "modified" : null,
    "published" : "2023-06-09",
    "duration" : 0,
    "abridged" : false,
    "conformsTo" : "https://readium.org/webpub-manifest/profiles/divina",
    "numberOfPages" : 173,
    "readingProgression" : "ttb",
    "belongsTo" : null,
    "presentation" : {
      "fit" : "width",
      "overflow" : "scrolled",
      "continuous" : true
    },
    "@type" : null,
    "schema:license" : null
  },
  "links" : [ {
    "rel" : "self",
    "href" : "https://raw.githubusercontent.com/thuvienonline40/book_storage_collection/main/comic_manifest.json",
    "type" : "application/divina+json"
  } ],
  "readingOrder" : [ {
    "href" : "https://raw.githubusercontent.com/duyhuynh652018/comic_storage5/main/IMAGE/IMAGE_4c04ba059f73aa1de16127ba173c8d73_baf932a4549cd372934a4370fa8a5f86_3dd8ea2715fa23dcc629fa5770c463ab.jpg",
    "type" : "image/jpeg",
    "bitrate" : 0,
    "duration" : 0,
    "title" : null,
    "properties" : null,
    "alternate" : [ {
      "href" : "https://i441.ntcdntempv26.com/data/images/18245/408777/001.jpg?data=net",
      "type" : "image/jpeg",
      "bitrate" : 0,
      "duration" : 0,
      "title" : null,
      "properties" : null,
      "alternate" : null
    } ]
  }, {
    "href" : "https://raw.githubusercontent.com/duyhuynh652018/comic_storage5/main/IMAGE/IMAGE_4c04ba059f73aa1de16127ba173c8d73_baf932a4549cd372934a4370fa8a5f86_7231312a03d11d34abb163fbc81e3e00.jpg",
    "type" : "image/jpeg",
    "bitrate" : 0,
    "duration" : 0,
    "title" : null,
    "properties" : null,
    "alternate" : [ {
      "href" : "https://i441.ntcdntempv26.com/data/images/18245/408777/002.jpg?data=net",
      "type" : "image/jpeg",
      "bitrate" : 0,
      "duration" : 0,
      "title" : null,
      "properties" : null,
      "alternate" : null
    } ]
  }, {
    "href" : "https://raw.githubusercontent.com/duyhuynh652018/comic_storage5/main/IMAGE/IMAGE_4c04ba059f73aa1de16127ba173c8d73_baf932a4549cd372934a4370fa8a5f86_4ecfaa29a95e99b5439b30d9e2460d79.jpg",
    "type" : "image/jpeg",
    "bitrate" : 0,
    "duration" : 0,
    "title" : null,
    "properties" : null,
    "alternate" : [ {
      "href" : "https://i441.ntcdntempv26.com/data/images/18245/408777/003.jpg?data=net",
      "type" : "image/jpeg",
      "bitrate" : 0,
      "duration" : 0,
      "title" : null,
      "properties" : null,
      "alternate" : null
    } ]
  }, {
    "href" : "https://raw.githubusercontent.com/duyhuynh652018/comic_storage5/main/IMAGE/IMAGE_4c04ba059f73aa1de16127ba173c8d73_baf932a4549cd372934a4370fa8a5f86_951ae4795576e6f9625435f312fbe43f.jpg",
    "type" : "image/jpeg",
    "bitrate" : 0,
    "duration" : 0,
    "title" : null,
    "properties" : null,
    "alternate" : [ {
      "href" : "https://i441.ntcdntempv26.com/data/images/18245/408777/004.jpg?data=net",
      "type" : "image/jpeg",
      "bitrate" : 0,
      "duration" : 0,
      "title" : null,
      "properties" : null,
      "alternate" : null
    } ]
  }, {
    "href" : "https://raw.githubusercontent.com/duyhuynh652018/comic_storage5/main/IMAGE/IMAGE_4c04ba059f73aa1de16127ba173c8d73_baf932a4549cd372934a4370fa8a5f86_16ea6f72ed6e76e1ec1761f937aee638.jpg",
    "type" : "image/jpeg",
    "bitrate" : 0,
    "duration" : 0,
    "title" : null,
    "properties" : null,
    "alternate" : [ {
      "href" : "https://i441.ntcdntempv26.com/data/images/18245/408777/005.jpg?data=net",
      "type" : "image/jpeg",
      "bitrate" : 0,
      "duration" : 0,
      "title" : null,
      "properties" : null,
      "alternate" : null
    } ]
  }, {
    "href" : "https://raw.githubusercontent.com/duyhuynh652018/comic_storage5/main/IMAGE/IMAGE_4c04ba059f73aa1de16127ba173c8d73_baf932a4549cd372934a4370fa8a5f86_4685442ed1e6c7f33dd1f2ddcf517c16.jpg",
    "type" : "image/jpeg",
    "bitrate" : 0,
    "duration" : 0,
    "title" : null,
    "properties" : null,
    "alternate" : [ {
      "href" : "https://i441.ntcdntempv26.com/data/images/18245/408777/006.jpg?data=net",
      "type" : "image/jpeg",
      "bitrate" : 0,
      "duration" : 0,
      "title" : null,
      "properties" : null,
      "alternate" : null
    } ]
  }, {
    "href" : "https://raw.githubusercontent.com/duyhuynh652018/comic_storage5/main/IMAGE/IMAGE_4c04ba059f73aa1de16127ba173c8d73_baf932a4549cd372934a4370fa8a5f86_d05901b2ee336034b0b6bb171a32b4ea.jpg",
    "type" : "image/jpeg",
    "bitrate" : 0,
    "duration" : 0,
    "title" : null,
    "properties" : null,
    "alternate" : [ {
      "href" : "https://i441.ntcdntempv26.com/data/images/18245/408777/007.jpg?data=net",
      "type" : "image/jpeg",
      "bitrate" : 0,
      "duration" : 0,
      "title" : null,
      "properties" : null,
      "alternate" : null
    } ]
  }, {
    "href" : "https://raw.githubusercontent.com/duyhuynh652018/comic_storage5/main/IMAGE/IMAGE_4c04ba059f73aa1de16127ba173c8d73_baf932a4549cd372934a4370fa8a5f86_ec8ce66fcbc5fe9ac18a5014c3a212a2.jpg",
    "type" : "image/jpeg",
    "bitrate" : 0,
    "duration" : 0,
    "title" : null,
    "properties" : null,
    "alternate" : [ {
      "href" : "https://i441.ntcdntempv26.com/data/images/18245/408777/008.jpg?data=net",
      "type" : "image/jpeg",
      "bitrate" : 0,
      "duration" : 0,
      "title" : null,
      "properties" : null,
      "alternate" : null
    } ]
  }, {
    "href" : "https://raw.githubusercontent.com/duyhuynh652018/comic_storage5/main/IMAGE/IMAGE_4c04ba059f73aa1de16127ba173c8d73_baf932a4549cd372934a4370fa8a5f86_744e892d28091ee19a40ac63b874975c.jpg",
    "type" : "image/jpeg",
    "bitrate" : 0,
    "duration" : 0,
    "title" : null,
    "properties" : null,
    "alternate" : [ {
      "href" : "https://i441.ntcdntempv26.com/data/images/18245/408777/009.jpg?data=net",
      "type" : "image/jpeg",
      "bitrate" : 0,
      "duration" : 0,
      "title" : null,
      "properties" : null,
      "alternate" : null
    } ]
  }, {
    "href" : "https://raw.githubusercontent.com/duyhuynh652018/comic_storage5/main/IMAGE/IMAGE_4c04ba059f73aa1de16127ba173c8d73_baf932a4549cd372934a4370fa8a5f86_a923444ca279316c05f1a45530481c47.jpg",
    "type" : "image/jpeg",
    "bitrate" : 0,
    "duration" : 0,
    "title" : null,
    "properties" : null,
    "alternate" : [ {
      "href" : "https://i441.ntcdntempv26.com/data/images/18245/408777/010.jpg?data=net",
      "type" : "image/jpeg",
      "bitrate" : 0,
      "duration" : 0,
      "title" : null,
      "properties" : null,
      "alternate" : null
    } ]
  }, {
    "href" : "https://raw.githubusercontent.com/duyhuynh652018/comic_storage5/main/IMAGE/IMAGE_4c04ba059f73aa1de16127ba173c8d73_baf932a4549cd372934a4370fa8a5f86_d165ac7c1975d6687d58d9650aae9258.jpg",
    "type" : "image/jpeg",
    "bitrate" : 0,
    "duration" : 0,
    "title" : null,
    "properties" : null,
    "alternate" : [ {
      "href" : "https://i441.ntcdntempv26.com/data/images/18245/408777/011.jpg?data=net",
      "type" : "image/jpeg",
      "bitrate" : 0,
      "duration" : 0,
      "title" : null,
      "properties" : null,
      "alternate" : null
    } ]
  }, {
    "href" : "https://raw.githubusercontent.com/duyhuynh652018/comic_storage5/main/IMAGE/IMAGE_4c04ba059f73aa1de16127ba173c8d73_baf932a4549cd372934a4370fa8a5f86_0d962f49719961ded2827adaf2727da6.jpg",
    "type" : "image/jpeg",
    "bitrate" : 0,
    "duration" : 0,
    "title" : null,
    "properties" : null,
    "alternate" : [ {
      "href" : "https://i441.ntcdntempv26.com/data/images/18245/408777/012.jpg?data=net",
      "type" : "image/jpeg",
      "bitrate" : 0,
      "duration" : 0,
      "title" : null,
      "properties" : null,
      "alternate" : null
    } ]
  }, {
    "href" : "https://raw.githubusercontent.com/duyhuynh652018/comic_storage5/main/IMAGE/IMAGE_4c04ba059f73aa1de16127ba173c8d73_baf932a4549cd372934a4370fa8a5f86_273e872509c340ab347af97ac4e86d26.jpg",
    "type" : "image/jpeg",
    "bitrate" : 0,
    "duration" : 0,
    "title" : null,
    "properties" : null,
    "alternate" : [ {
      "href" : "https://i441.ntcdntempv26.com/data/images/18245/408777/013.jpg?data=net",
      "type" : "image/jpeg",
      "bitrate" : 0,
      "duration" : 0,
      "title" : null,
      "properties" : null,
      "alternate" : null
    } ]
  }, {
    "href" : "https://raw.githubusercontent.com/duyhuynh652018/comic_storage5/main/IMAGE/IMAGE_4c04ba059f73aa1de16127ba173c8d73_baf932a4549cd372934a4370fa8a5f86_a7da9a15c6af531f997a79be3ad28aa0.jpg",
    "type" : "image/jpeg",
    "bitrate" : 0,
    "duration" : 0,
    "title" : null,
    "properties" : null,
    "alternate" : [ {
      "href" : "https://i441.ntcdntempv26.com/data/images/18245/408777/014.jpg?data=net",
      "type" : "image/jpeg",
      "bitrate" : 0,
      "duration" : 0,
      "title" : null,
      "properties" : null,
      "alternate" : null
    } ]
  }, {
    "href" : "https://raw.githubusercontent.com/duyhuynh652018/comic_storage5/main/IMAGE/IMAGE_4c04ba059f73aa1de16127ba173c8d73_baf932a4549cd372934a4370fa8a5f86_1e37a88ca8677ce1a6a173e77561c382.jpg",
    "type" : "image/jpeg",
    "bitrate" : 0,
    "duration" : 0,
    "title" : null,
    "properties" : null,
    "alternate" : [ {
      "href" : "https://i441.ntcdntempv26.com/data/images/18245/408777/015.jpg?data=net",
      "type" : "image/jpeg",
      "bitrate" : 0,
      "duration" : 0,
      "title" : null,
      "properties" : null,
      "alternate" : null
    } ]
  }, {
    "href" : "https://raw.githubusercontent.com/duyhuynh652018/comic_storage5/main/IMAGE/IMAGE_4c04ba059f73aa1de16127ba173c8d73_baf932a4549cd372934a4370fa8a5f86_d86999b59362b73bbe02c068980b07e4.jpg",
    "type" : "image/jpeg",
    "bitrate" : 0,
    "duration" : 0,
    "title" : null,
    "properties" : null,
    "alternate" : [ {
      "href" : "https://i441.ntcdntempv26.com/data/images/18245/408777/016.jpg?data=net",
      "type" : "image/jpeg",
      "bitrate" : 0,
      "duration" : 0,
      "title" : null,
      "properties" : null,
      "alternate" : null
    } ]
  }, {
    "href" : "https://raw.githubusercontent.com/duyhuynh652018/comic_storage5/main/IMAGE/IMAGE_4c04ba059f73aa1de16127ba173c8d73_baf932a4549cd372934a4370fa8a5f86_9ce331104d817ed1f1c4aeb490dfc40f.jpg",
    "type" : "image/jpeg",
    "bitrate" : 0,
    "duration" : 0,
    "title" : null,
    "properties" : null,
    "alternate" : [ {
      "href" : "https://i441.ntcdntempv26.com/data/images/18245/408777/017.jpg?data=net",
      "type" : "image/jpeg",
      "bitrate" : 0,
      "duration" : 0,
      "title" : null,
      "properties" : null,
      "alternate" : null
    } ]
  }, {
    "href" : "https://raw.githubusercontent.com/duyhuynh652018/comic_storage5/main/IMAGE/IMAGE_4c04ba059f73aa1de16127ba173c8d73_baf932a4549cd372934a4370fa8a5f86_f7f4023df429422eda2ba74cfe9d7c6b.jpg",
    "type" : "image/jpeg",
    "bitrate" : 0,
    "duration" : 0,
    "title" : null,
    "properties" : null,
    "alternate" : [ {
      "href" : "https://i441.ntcdntempv26.com/data/images/18245/408777/018.jpg?data=net",
      "type" : "image/jpeg",
      "bitrate" : 0,
      "duration" : 0,
      "title" : null,
      "properties" : null,
      "alternate" : null
    } ]
  }, {
    "href" : "https://raw.githubusercontent.com/duyhuynh652018/comic_storage5/main/IMAGE/IMAGE_4c04ba059f73aa1de16127ba173c8d73_baf932a4549cd372934a4370fa8a5f86_290fcfe8d7fe2d354a69ae969d451677.jpg",
    "type" : "image/jpeg",
    "bitrate" : 0,
    "duration" : 0,
    "title" : null,
    "properties" : null,
    "alternate" : [ {
      "href" : "https://i441.ntcdntempv26.com/data/images/18245/408777/019.jpg?data=net",
      "type" : "image/jpeg",
      "bitrate" : 0,
      "duration" : 0,
      "title" : null,
      "properties" : null,
      "alternate" : null
    } ]
  }, {
    "href" : "https://raw.githubusercontent.com/duyhuynh652018/comic_storage5/main/IMAGE/IMAGE_4c04ba059f73aa1de16127ba173c8d73_baf932a4549cd372934a4370fa8a5f86_6ba8ef7a5594e0b9399359b0a94ad36f.jpg",
    "type" : "image/jpeg",
    "bitrate" : 0,
    "duration" : 0,
    "title" : null,
    "properties" : null,
    "alternate" : [ {
      "href" : "https://i441.ntcdntempv26.com/data/images/18245/408777/020.jpg?data=net",
      "type" : "image/jpeg",
      "bitrate" : 0,
      "duration" : 0,
      "title" : null,
      "properties" : null,
      "alternate" : null
    } ]
  }, {
    "href" : "https://raw.githubusercontent.com/duyhuynh652018/comic_storage5/main/IMAGE/IMAGE_4c04ba059f73aa1de16127ba173c8d73_baf932a4549cd372934a4370fa8a5f86_87671671fa36d6041f4bcb7fa26f1828.jpg",
    "type" : "image/jpeg",
    "bitrate" : 0,
    "duration" : 0,
    "title" : null,
    "properties" : null,
    "alternate" : [ {
      "href" : "https://i441.ntcdntempv26.com/data/images/18245/408777/021.jpg?data=net",
      "type" : "image/jpeg",
      "bitrate" : 0,
      "duration" : 0,
      "title" : null,
      "properties" : null,
      "alternate" : null
    } ]
  }, {
    "href" : "https://raw.githubusercontent.com/duyhuynh652018/comic_storage5/main/IMAGE/IMAGE_4c04ba059f73aa1de16127ba173c8d73_baf932a4549cd372934a4370fa8a5f86_1c332ed0b6d3aa41d8ccc66d0f5fa2a9.jpg",
    "type" : "image/jpeg",
    "bitrate" : 0,
    "duration" : 0,
    "title" : null,
    "properties" : null,
    "alternate" : [ {
      "href" : "https://i441.ntcdntempv26.com/data/images/18245/408777/022.jpg?data=net",
      "type" : "image/jpeg",
      "bitrate" : 0,
      "duration" : 0,
      "title" : null,
      "properties" : null,
      "alternate" : null
    } ]
  }, {
    "href" : "https://raw.githubusercontent.com/duyhuynh652018/comic_storage5/main/IMAGE/IMAGE_4c04ba059f73aa1de16127ba173c8d73_baf932a4549cd372934a4370fa8a5f86_94b91feed1a4481a028f04da6764b745.jpg",
    "type" : "image/jpeg",
    "bitrate" : 0,
    "duration" : 0,
    "title" : null,
    "properties" : null,
    "alternate" : [ {
      "href" : "https://i441.ntcdntempv26.com/data/images/18245/408777/023.jpg?data=net",
      "type" : "image/jpeg",
      "bitrate" : 0,
      "duration" : 0,
      "title" : null,
      "properties" : null,
      "alternate" : null
    } ]
  }, {
    "href" : "https://raw.githubusercontent.com/duyhuynh652018/comic_storage5/main/IMAGE/IMAGE_4c04ba059f73aa1de16127ba173c8d73_baf932a4549cd372934a4370fa8a5f86_85c17b589194a068e0b5e4e0039850d9.jpg",
    "type" : "image/jpeg",
    "bitrate" : 0,
    "duration" : 0,
    "title" : null,
    "properties" : null,
    "alternate" : [ {
      "href" : "https://i441.ntcdntempv26.com/data/images/18245/408777/024.jpg?data=net",
      "type" : "image/jpeg",
      "bitrate" : 0,
      "duration" : 0,
      "title" : null,
      "properties" : null,
      "alternate" : null
    } ]
  }, {
    "href" : "https://raw.githubusercontent.com/duyhuynh652018/comic_storage5/main/IMAGE/IMAGE_4c04ba059f73aa1de16127ba173c8d73_baf932a4549cd372934a4370fa8a5f86_44f6920b2b6d4ebe114becfc257b8e13.jpg",
    "type" : "image/jpeg",
    "bitrate" : 0,
    "duration" : 0,
    "title" : null,
    "properties" : null,
    "alternate" : [ {
      "href" : "https://i441.ntcdntempv26.com/data/images/18245/408777/025.jpg?data=net",
      "type" : "image/jpeg",
      "bitrate" : 0,
      "duration" : 0,
      "title" : null,
      "properties" : null,
      "alternate" : null
    } ]
  }, {
    "href" : "https://raw.githubusercontent.com/duyhuynh652018/comic_storage5/main/IMAGE/IMAGE_4c04ba059f73aa1de16127ba173c8d73_baf932a4549cd372934a4370fa8a5f86_7e76f5d11cc8b05a8681bff3a5108465.jpg",
    "type" : "image/jpeg",
    "bitrate" : 0,
    "duration" : 0,
    "title" : null,
    "properties" : null,
    "alternate" : [ {
      "href" : "https://i441.ntcdntempv26.com/data/images/18245/408777/026.jpg?data=net",
      "type" : "image/jpeg",
      "bitrate" : 0,
      "duration" : 0,
      "title" : null,
      "properties" : null,
      "alternate" : null
    } ]
  }, {
    "href" : "https://raw.githubusercontent.com/duyhuynh652018/comic_storage5/main/IMAGE/IMAGE_4c04ba059f73aa1de16127ba173c8d73_baf932a4549cd372934a4370fa8a5f86_57bd5febc569c26f90d9564e5b2be22f.jpg",
    "type" : "image/jpeg",
    "bitrate" : 0,
    "duration" : 0,
    "title" : null,
    "properties" : null,
    "alternate" : [ {
      "href" : "https://i441.ntcdntempv26.com/data/images/18245/408777/027.jpg?data=net",
      "type" : "image/jpeg",
      "bitrate" : 0,
      "duration" : 0,
      "title" : null,
      "properties" : null,
      "alternate" : null
    } ]
  }, {
    "href" : "https://raw.githubusercontent.com/duyhuynh652018/comic_storage5/main/IMAGE/IMAGE_4c04ba059f73aa1de16127ba173c8d73_baf932a4549cd372934a4370fa8a5f86_fd7de4f4968446af8e09d6cbd2d5878a.jpg",
    "type" : "image/jpeg",
    "bitrate" : 0,
    "duration" : 0,
    "title" : null,
    "properties" : null,
    "alternate" : [ {
      "href" : "https://i441.ntcdntempv26.com/data/images/18245/408777/028.jpg?data=net",
      "type" : "image/jpeg",
      "bitrate" : 0,
      "duration" : 0,
      "title" : null,
      "properties" : null,
      "alternate" : null
    } ]
  }, {
    "href" : "https://raw.githubusercontent.com/duyhuynh652018/comic_storage5/main/IMAGE/IMAGE_4c04ba059f73aa1de16127ba173c8d73_baf932a4549cd372934a4370fa8a5f86_041eebbc683ff617581c93fe2217b585.jpg",
    "type" : "image/jpeg",
    "bitrate" : 0,
    "duration" : 0,
    "title" : null,
    "properties" : null,
    "alternate" : [ {
      "href" : "https://i441.ntcdntempv26.com/data/images/18245/408777/029.jpg?data=net",
      "type" : "image/jpeg",
      "bitrate" : 0,
      "duration" : 0,
      "title" : null,
      "properties" : null,
      "alternate" : null
    } ]
  }, {
    "href" : "https://raw.githubusercontent.com/duyhuynh652018/comic_storage5/main/IMAGE/IMAGE_4c04ba059f73aa1de16127ba173c8d73_baf932a4549cd372934a4370fa8a5f86_f2cd9a6219ea4baf393c1572ebe561b2.jpg",
    "type" : "image/jpeg",
    "bitrate" : 0,
    "duration" : 0,
    "title" : null,
    "properties" : null,
    "alternate" : [ {
      "href" : "https://i441.ntcdntempv26.com/data/images/18245/408777/030.jpg?data=net",
      "type" : "image/jpeg",
      "bitrate" : 0,
      "duration" : 0,
      "title" : null,
      "properties" : null,
      "alternate" : null
    } ]
  }, {
    "href" : "https://raw.githubusercontent.com/duyhuynh652018/comic_storage5/main/IMAGE/IMAGE_4c04ba059f73aa1de16127ba173c8d73_baf932a4549cd372934a4370fa8a5f86_54df0cccb830be49ec7be2a57bd7f51e.jpg",
    "type" : "image/jpeg",
    "bitrate" : 0,
    "duration" : 0,
    "title" : null,
    "properties" : null,
    "alternate" : [ {
      "href" : "https://i441.ntcdntempv26.com/data/images/18245/408777/031.jpg?data=net",
      "type" : "image/jpeg",
      "bitrate" : 0,
      "duration" : 0,
      "title" : null,
      "properties" : null,
      "alternate" : null
    } ]
  }, {
    "href" : "https://raw.githubusercontent.com/duyhuynh652018/comic_storage5/main/IMAGE/IMAGE_4c04ba059f73aa1de16127ba173c8d73_baf932a4549cd372934a4370fa8a5f86_9cb2bced3c438fe3a70fbd29bcdaf7df.jpg",
    "type" : "image/jpeg",
    "bitrate" : 0,
    "duration" : 0,
    "title" : null,
    "properties" : null,
    "alternate" : [ {
      "href" : "https://i441.ntcdntempv26.com/data/images/18245/408777/032.jpg?data=net",
      "type" : "image/jpeg",
      "bitrate" : 0,
      "duration" : 0,
      "title" : null,
      "properties" : null,
      "alternate" : null
    } ]
  }, {
    "href" : "https://raw.githubusercontent.com/duyhuynh652018/comic_storage5/main/IMAGE/IMAGE_4c04ba059f73aa1de16127ba173c8d73_baf932a4549cd372934a4370fa8a5f86_771846d90863cb799bf461ab0cfc5c65.jpg",
    "type" : "image/jpeg",
    "bitrate" : 0,
    "duration" : 0,
    "title" : null,
    "properties" : null,
    "alternate" : [ {
      "href" : "https://i441.ntcdntempv26.com/data/images/18245/408777/033.jpg?data=net",
      "type" : "image/jpeg",
      "bitrate" : 0,
      "duration" : 0,
      "title" : null,
      "properties" : null,
      "alternate" : null
    } ]
  }, {
    "href" : "https://raw.githubusercontent.com/duyhuynh652018/comic_storage5/main/IMAGE/IMAGE_4c04ba059f73aa1de16127ba173c8d73_baf932a4549cd372934a4370fa8a5f86_9ab2ceb5b868ea363ac1a03276892707.jpg",
    "type" : "image/jpeg",
    "bitrate" : 0,
    "duration" : 0,
    "title" : null,
    "properties" : null,
    "alternate" : [ {
      "href" : "https://i441.ntcdntempv26.com/data/images/18245/408777/034.jpg?data=net",
      "type" : "image/jpeg",
      "bitrate" : 0,
      "duration" : 0,
      "title" : null,
      "properties" : null,
      "alternate" : null
    } ]
  }, {
    "href" : "https://raw.githubusercontent.com/duyhuynh652018/comic_storage5/main/IMAGE/IMAGE_4c04ba059f73aa1de16127ba173c8d73_baf932a4549cd372934a4370fa8a5f86_961a35562ed2e86722b83015b7005eaf.jpg",
    "type" : "image/jpeg",
    "bitrate" : 0,
    "duration" : 0,
    "title" : null,
    "properties" : null,
    "alternate" : [ {
      "href" : "https://i441.ntcdntempv26.com/data/images/18245/408777/035.jpg?data=net",
      "type" : "image/jpeg",
      "bitrate" : 0,
      "duration" : 0,
      "title" : null,
      "properties" : null,
      "alternate" : null
    } ]
  }, {
    "href" : "https://raw.githubusercontent.com/duyhuynh652018/comic_storage5/main/IMAGE/IMAGE_4c04ba059f73aa1de16127ba173c8d73_baf932a4549cd372934a4370fa8a5f86_c3577e5a50788c0ededb1150506c10e3.jpg",
    "type" : "image/jpeg",
    "bitrate" : 0,
    "duration" : 0,
    "title" : null,
    "properties" : null,
    "alternate" : [ {
      "href" : "https://i441.ntcdntempv26.com/data/images/18245/408777/036.jpg?data=net",
      "type" : "image/jpeg",
      "bitrate" : 0,
      "duration" : 0,
      "title" : null,
      "properties" : null,
      "alternate" : null
    } ]
  }, {
    "href" : "https://raw.githubusercontent.com/duyhuynh652018/comic_storage5/main/IMAGE/IMAGE_4c04ba059f73aa1de16127ba173c8d73_baf932a4549cd372934a4370fa8a5f86_6807a676556960db70b8f67342432c38.jpg",
    "type" : "image/jpeg",
    "bitrate" : 0,
    "duration" : 0,
    "title" : null,
    "properties" : null,
    "alternate" : [ {
      "href" : "https://i441.ntcdntempv26.com/data/images/18245/408777/037.jpg?data=net",
      "type" : "image/jpeg",
      "bitrate" : 0,
      "duration" : 0,
      "title" : null,
      "properties" : null,
      "alternate" : null
    } ]
  }, {
    "href" : "https://raw.githubusercontent.com/duyhuynh652018/comic_storage5/main/IMAGE/IMAGE_4c04ba059f73aa1de16127ba173c8d73_baf932a4549cd372934a4370fa8a5f86_7c27c06485e12d5c45385eaad6874f53.jpg",
    "type" : "image/jpeg",
    "bitrate" : 0,
    "duration" : 0,
    "title" : null,
    "properties" : null,
    "alternate" : [ {
      "href" : "https://i441.ntcdntempv26.com/data/images/18245/408777/038.jpg?data=net",
      "type" : "image/jpeg",
      "bitrate" : 0,
      "duration" : 0,
      "title" : null,
      "properties" : null,
      "alternate" : null
    } ]
  }, {
    "href" : "https://raw.githubusercontent.com/duyhuynh652018/comic_storage5/main/IMAGE/IMAGE_4c04ba059f73aa1de16127ba173c8d73_baf932a4549cd372934a4370fa8a5f86_0da11042f37918bacfb8a49f2199267f.jpg",
    "type" : "image/jpeg",
    "bitrate" : 0,
    "duration" : 0,
    "title" : null,
    "properties" : null,
    "alternate" : [ {
      "href" : "https://i441.ntcdntempv26.com/data/images/18245/408777/039.jpg?data=net",
      "type" : "image/jpeg",
      "bitrate" : 0,
      "duration" : 0,
      "title" : null,
      "properties" : null,
      "alternate" : null
    } ]
  }, {
    "href" : "https://raw.githubusercontent.com/duyhuynh652018/comic_storage5/main/IMAGE/IMAGE_4c04ba059f73aa1de16127ba173c8d73_baf932a4549cd372934a4370fa8a5f86_de1887d3543a83798e5ab1a98fd0a147.jpg",
    "type" : "image/jpeg",
    "bitrate" : 0,
    "duration" : 0,
    "title" : null,
    "properties" : null,
    "alternate" : [ {
      "href" : "https://i441.ntcdntempv26.com/data/images/18245/408777/040.jpg?data=net",
      "type" : "image/jpeg",
      "bitrate" : 0,
      "duration" : 0,
      "title" : null,
      "properties" : null,
      "alternate" : null
    } ]
  }, {
    "href" : "https://raw.githubusercontent.com/duyhuynh652018/comic_storage5/main/IMAGE/IMAGE_4c04ba059f73aa1de16127ba173c8d73_baf932a4549cd372934a4370fa8a5f86_fa054a62902d56d1e554c4ddfeee1ece.jpg",
    "type" : "image/jpeg",
    "bitrate" : 0,
    "duration" : 0,
    "title" : null,
    "properties" : null,
    "alternate" : [ {
      "href" : "https://i441.ntcdntempv26.com/data/images/18245/408777/041.jpg?data=net",
      "type" : "image/jpeg",
      "bitrate" : 0,
      "duration" : 0,
      "title" : null,
      "properties" : null,
      "alternate" : null
    } ]
  }, {
    "href" : "https://raw.githubusercontent.com/duyhuynh652018/comic_storage5/main/IMAGE/IMAGE_4c04ba059f73aa1de16127ba173c8d73_baf932a4549cd372934a4370fa8a5f86_390b0caf97a5c6adc3cb99107fe53564.jpg",
    "type" : "image/jpeg",
    "bitrate" : 0,
    "duration" : 0,
    "title" : null,
    "properties" : null,
    "alternate" : [ {
      "href" : "https://i441.ntcdntempv26.com/data/images/18245/408777/042.jpg?data=net",
      "type" : "image/jpeg",
      "bitrate" : 0,
      "duration" : 0,
      "title" : null,
      "properties" : null,
      "alternate" : null
    } ]
  }, {
    "href" : "https://raw.githubusercontent.com/duyhuynh652018/comic_storage5/main/IMAGE/IMAGE_4c04ba059f73aa1de16127ba173c8d73_baf932a4549cd372934a4370fa8a5f86_eccfa7db74f25b6267c9e094bf8d7655.jpg",
    "type" : "image/jpeg",
    "bitrate" : 0,
    "duration" : 0,
    "title" : null,
    "properties" : null,
    "alternate" : [ {
      "href" : "https://i441.ntcdntempv26.com/data/images/18245/408777/043.jpg?data=net",
      "type" : "image/jpeg",
      "bitrate" : 0,
      "duration" : 0,
      "title" : null,
      "properties" : null,
      "alternate" : null
    } ]
  }, {
    "href" : "https://raw.githubusercontent.com/duyhuynh652018/comic_storage5/main/IMAGE/IMAGE_4c04ba059f73aa1de16127ba173c8d73_baf932a4549cd372934a4370fa8a5f86_abf567946ff4f9572a132071be959381.jpg",
    "type" : "image/jpeg",
    "bitrate" : 0,
    "duration" : 0,
    "title" : null,
    "properties" : null,
    "alternate" : [ {
      "href" : "https://i441.ntcdntempv26.com/data/images/18245/408777/044.jpg?data=net",
      "type" : "image/jpeg",
      "bitrate" : 0,
      "duration" : 0,
      "title" : null,
      "properties" : null,
      "alternate" : null
    } ]
  }, {
    "href" : "https://raw.githubusercontent.com/duyhuynh652018/comic_storage5/main/IMAGE/IMAGE_4c04ba059f73aa1de16127ba173c8d73_baf932a4549cd372934a4370fa8a5f86_22ca63fe67e85c81a022a9594138135b.jpg",
    "type" : "image/jpeg",
    "bitrate" : 0,
    "duration" : 0,
    "title" : null,
    "properties" : null,
    "alternate" : [ {
      "href" : "https://i441.ntcdntempv26.com/data/images/18245/408777/045.jpg?data=net",
      "type" : "image/jpeg",
      "bitrate" : 0,
      "duration" : 0,
      "title" : null,
      "properties" : null,
      "alternate" : null
    } ]
  }, {
    "href" : "https://raw.githubusercontent.com/duyhuynh652018/comic_storage5/main/IMAGE/IMAGE_4c04ba059f73aa1de16127ba173c8d73_baf932a4549cd372934a4370fa8a5f86_90715515363906e87724f59e4c6a090f.jpg",
    "type" : "image/jpeg",
    "bitrate" : 0,
    "duration" : 0,
    "title" : null,
    "properties" : null,
    "alternate" : [ {
      "href" : "https://i441.ntcdntempv26.com/data/images/18245/408777/046.jpg?data=net",
      "type" : "image/jpeg",
      "bitrate" : 0,
      "duration" : 0,
      "title" : null,
      "properties" : null,
      "alternate" : null
    } ]
  }, {
    "href" : "https://raw.githubusercontent.com/duyhuynh652018/comic_storage5/main/IMAGE/IMAGE_4c04ba059f73aa1de16127ba173c8d73_baf932a4549cd372934a4370fa8a5f86_4d8a83517a8d0694d96a8d766407d98f.jpg",
    "type" : "image/jpeg",
    "bitrate" : 0,
    "duration" : 0,
    "title" : null,
    "properties" : null,
    "alternate" : [ {
      "href" : "https://i441.ntcdntempv26.com/data/images/18245/408777/047.jpg?data=net",
      "type" : "image/jpeg",
      "bitrate" : 0,
      "duration" : 0,
      "title" : null,
      "properties" : null,
      "alternate" : null
    } ]
  }, {
    "href" : "https://raw.githubusercontent.com/duyhuynh652018/comic_storage5/main/IMAGE/IMAGE_4c04ba059f73aa1de16127ba173c8d73_baf932a4549cd372934a4370fa8a5f86_97f6ef955373360d107991be56ddf49d.jpg",
    "type" : "image/jpeg",
    "bitrate" : 0,
    "duration" : 0,
    "title" : null,
    "properties" : null,
    "alternate" : [ {
      "href" : "https://i441.ntcdntempv26.com/data/images/18245/408777/048.jpg?data=net",
      "type" : "image/jpeg",
      "bitrate" : 0,
      "duration" : 0,
      "title" : null,
      "properties" : null,
      "alternate" : null
    } ]
  }, {
    "href" : "https://raw.githubusercontent.com/duyhuynh652018/comic_storage5/main/IMAGE/IMAGE_4c04ba059f73aa1de16127ba173c8d73_baf932a4549cd372934a4370fa8a5f86_1cdc92605e72134f46e670246aff76d1.jpg",
    "type" : "image/jpeg",
    "bitrate" : 0,
    "duration" : 0,
    "title" : null,
    "properties" : null,
    "alternate" : [ {
      "href" : "https://i441.ntcdntempv26.com/data/images/18245/408777/049.jpg?data=net",
      "type" : "image/jpeg",
      "bitrate" : 0,
      "duration" : 0,
      "title" : null,
      "properties" : null,
      "alternate" : null
    } ]
  }, {
    "href" : "https://raw.githubusercontent.com/duyhuynh652018/comic_storage5/main/IMAGE/IMAGE_4c04ba059f73aa1de16127ba173c8d73_baf932a4549cd372934a4370fa8a5f86_fd55265f141c80037b72be717a4b8563.jpg",
    "type" : "image/jpeg",
    "bitrate" : 0,
    "duration" : 0,
    "title" : null,
    "properties" : null,
    "alternate" : [ {
      "href" : "https://i441.ntcdntempv26.com/data/images/18245/408777/050.jpg?data=net",
      "type" : "image/jpeg",
      "bitrate" : 0,
      "duration" : 0,
      "title" : null,
      "properties" : null,
      "alternate" : null
    } ]
  }, {
    "href" : "https://raw.githubusercontent.com/duyhuynh652018/comic_storage5/main/IMAGE/IMAGE_4c04ba059f73aa1de16127ba173c8d73_baf932a4549cd372934a4370fa8a5f86_8057d104d5f1ad39a5706b8bca7af6bc.jpg",
    "type" : "image/jpeg",
    "bitrate" : 0,
    "duration" : 0,
    "title" : null,
    "properties" : null,
    "alternate" : [ {
      "href" : "https://i441.ntcdntempv26.com/data/images/18245/408777/051.jpg?data=net",
      "type" : "image/jpeg",
      "bitrate" : 0,
      "duration" : 0,
      "title" : null,
      "properties" : null,
      "alternate" : null
    } ]
  }, {
    "href" : "https://raw.githubusercontent.com/duyhuynh652018/comic_storage5/main/IMAGE/IMAGE_4c04ba059f73aa1de16127ba173c8d73_baf932a4549cd372934a4370fa8a5f86_b537293537f398e6e6369158cbef3d46.jpg",
    "type" : "image/jpeg",
    "bitrate" : 0,
    "duration" : 0,
    "title" : null,
    "properties" : null,
    "alternate" : [ {
      "href" : "https://i441.ntcdntempv26.com/data/images/18245/408777/052.jpg?data=net",
      "type" : "image/jpeg",
      "bitrate" : 0,
      "duration" : 0,
      "title" : null,
      "properties" : null,
      "alternate" : null
    } ]
  }, {
    "href" : "https://raw.githubusercontent.com/duyhuynh652018/comic_storage5/main/IMAGE/IMAGE_4c04ba059f73aa1de16127ba173c8d73_baf932a4549cd372934a4370fa8a5f86_80c1df88bb86b09959ca05a1be09fcc3.jpg",
    "type" : "image/jpeg",
    "bitrate" : 0,
    "duration" : 0,
    "title" : null,
    "properties" : null,
    "alternate" : [ {
      "href" : "https://i441.ntcdntempv26.com/data/images/18245/408777/053.jpg?data=net",
      "type" : "image/jpeg",
      "bitrate" : 0,
      "duration" : 0,
      "title" : null,
      "properties" : null,
      "alternate" : null
    } ]
  }, {
    "href" : "https://raw.githubusercontent.com/duyhuynh652018/comic_storage5/main/IMAGE/IMAGE_4c04ba059f73aa1de16127ba173c8d73_baf932a4549cd372934a4370fa8a5f86_7d7fce3d4a3b51af26ecc354699a7fb9.jpg",
    "type" : "image/jpeg",
    "bitrate" : 0,
    "duration" : 0,
    "title" : null,
    "properties" : null,
    "alternate" : [ {
      "href" : "https://i441.ntcdntempv26.com/data/images/18245/408777/054.jpg?data=net",
      "type" : "image/jpeg",
      "bitrate" : 0,
      "duration" : 0,
      "title" : null,
      "properties" : null,
      "alternate" : null
    } ]
  }, {
    "href" : "https://raw.githubusercontent.com/duyhuynh652018/comic_storage5/main/IMAGE/IMAGE_4c04ba059f73aa1de16127ba173c8d73_baf932a4549cd372934a4370fa8a5f86_914d51f91d1f931916559e91d73d046b.jpg",
    "type" : "image/jpeg",
    "bitrate" : 0,
    "duration" : 0,
    "title" : null,
    "properties" : null,
    "alternate" : [ {
      "href" : "https://i441.ntcdntempv26.com/data/images/18245/408777/055.jpg?data=net",
      "type" : "image/jpeg",
      "bitrate" : 0,
      "duration" : 0,
      "title" : null,
      "properties" : null,
      "alternate" : null
    } ]
  }, {
    "href" : "https://raw.githubusercontent.com/duyhuynh652018/comic_storage5/main/IMAGE/IMAGE_4c04ba059f73aa1de16127ba173c8d73_baf932a4549cd372934a4370fa8a5f86_f0f686564958363dd5d97772b3ea69bf.jpg",
    "type" : "image/jpeg",
    "bitrate" : 0,
    "duration" : 0,
    "title" : null,
    "properties" : null,
    "alternate" : [ {
      "href" : "https://i441.ntcdntempv26.com/data/images/18245/408777/056.jpg?data=net",
      "type" : "image/jpeg",
      "bitrate" : 0,
      "duration" : 0,
      "title" : null,
      "properties" : null,
      "alternate" : null
    } ]
  }, {
    "href" : "https://raw.githubusercontent.com/duyhuynh652018/comic_storage5/main/IMAGE/IMAGE_4c04ba059f73aa1de16127ba173c8d73_baf932a4549cd372934a4370fa8a5f86_fecea0e00566241c3d3719186fd25737.jpg",
    "type" : "image/jpeg",
    "bitrate" : 0,
    "duration" : 0,
    "title" : null,
    "properties" : null,
    "alternate" : [ {
      "href" : "https://i441.ntcdntempv26.com/data/images/18245/408777/057.jpg?data=net",
      "type" : "image/jpeg",
      "bitrate" : 0,
      "duration" : 0,
      "title" : null,
      "properties" : null,
      "alternate" : null
    } ]
  }, {
    "href" : "https://raw.githubusercontent.com/duyhuynh652018/comic_storage5/main/IMAGE/IMAGE_4c04ba059f73aa1de16127ba173c8d73_baf932a4549cd372934a4370fa8a5f86_b8642e5d1ea8fe8aac4015dc86dbbb96.jpg",
    "type" : "image/jpeg",
    "bitrate" : 0,
    "duration" : 0,
    "title" : null,
    "properties" : null,
    "alternate" : [ {
      "href" : "https://i441.ntcdntempv26.com/data/images/18245/408777/058.jpg?data=net",
      "type" : "image/jpeg",
      "bitrate" : 0,
      "duration" : 0,
      "title" : null,
      "properties" : null,
      "alternate" : null
    } ]
  }, {
    "href" : "https://raw.githubusercontent.com/duyhuynh652018/comic_storage5/main/IMAGE/IMAGE_4c04ba059f73aa1de16127ba173c8d73_baf932a4549cd372934a4370fa8a5f86_932fe8dab4abac3189e75bfdb4275cd3.jpg",
    "type" : "image/jpeg",
    "bitrate" : 0,
    "duration" : 0,
    "title" : null,
    "properties" : null,
    "alternate" : [ {
      "href" : "https://i441.ntcdntempv26.com/data/images/18245/408777/059.jpg?data=net",
      "type" : "image/jpeg",
      "bitrate" : 0,
      "duration" : 0,
      "title" : null,
      "properties" : null,
      "alternate" : null
    } ]
  }, {
    "href" : "https://raw.githubusercontent.com/duyhuynh652018/comic_storage5/main/IMAGE/IMAGE_4c04ba059f73aa1de16127ba173c8d73_baf932a4549cd372934a4370fa8a5f86_ca02cebad4f6f94a7d120ae997db1d13.jpg",
    "type" : "image/jpeg",
    "bitrate" : 0,
    "duration" : 0,
    "title" : null,
    "properties" : null,
    "alternate" : [ {
      "href" : "https://i441.ntcdntempv26.com/data/images/18245/408777/060.jpg?data=net",
      "type" : "image/jpeg",
      "bitrate" : 0,
      "duration" : 0,
      "title" : null,
      "properties" : null,
      "alternate" : null
    } ]
  } ],
  "toc" : null,
  "@context" : "https://readium.org/webpub-manifest/context.jsonld"
}