{
  "metadata" : {
    "identifier" : "https://nghetruyenma.net/dau-chan-quy-du.html",
    "title" : "Dấu Chân Quỷ Dữ",
    "subtitle" : "N/A",
    "author" : {
      "name" : "Tuấn Vũ",
      "sortAs" : ""
    },
    "narrator" : "N/A",
    "language" : "vi",
    "description" : "N/A",
    "publisher" : "N/A",
    "subject" : null,
    "modified" : null,
    "published" : "2023-06-27",
    "duration" : 4254,
    "abridged" : false,
    "conformsTo" : null,
    "numberOfPages" : null,
    "readingProgression" : null,
    "belongsTo" : null,
    "presentation" : null,
    "@type" : "http://schema.org/Audiobook",
    "schema:license" : "https://creativecommons.org/publicdomain/zero/1.0/"
  },
  "links" : [ {
    "rel" : "self",
    "href" : "https://raw.githubusercontent.com/vietduyhuynh90s/book_storage_two5/main/EPUB/EPUB_8e6d8be2b9ad74e83539a6d2bf3466ca.json",
    "type" : "application/audiobook+json"
  }, {
    "rel" : "cover",
    "href" : "https://raw.githubusercontent.com/vietduyhuynh90s/book_storage_two5/main/IMAGE/IMAGE_8e6d8be2b9ad74e83539a6d2bf3466ca.webp",
    "type" : "image/jpeg",
    "height" : 300,
    "width" : 300
  } ],
  "readingOrder" : [ {
    "href" : "https://archive.org/download/dau-chan-quy-du/dau-chan-quy-du.mp3",
    "type" : "audio/mpeg",
    "bitrate" : 128,
    "duration" : 4254,
    "title" : "dau-chan-quy-du",
    "properties" : null,
    "alternate" : null
  } ],
  "toc" : [ {
    "href" : "https://archive.org/download/dau-chan-quy-du/dau-chan-quy-du.mp3",
    "title" : "dau-chan-quy-du",
    "children" : [ ]
  } ],
  "@context" : "https://readium.org/webpub-manifest/context.jsonld"
}